__about__.py
colors.py
main.py
setup.py
analyzer/__init__.py
analyzer/analyzer.py
analyzer/analyzer_test.py
analyzer/regex.py
ghast_scanner-1.8.8.dist-info/METADATA
ghast_scanner-1.8.8.dist-info/WHEEL
ghast_scanner-1.8.8.dist-info/entry_points.txt
ghast_scanner-1.8.8.dist-info/licenses/LICENSE
ghast_scanner-1.8.8.dist-info/RECORD
