Metadata-Version: 2.1
Name: ghast-scanner
Version: 1.8.8
Summary: Analyze the security posture of your GitHub Actions
Project-URL: Documentation, https://github.com/bin3xish477/ghast#readme
Project-URL: Issues, https://github.com/bin3xish477/ghast/issues
Project-URL: Source, https://github.com/bin3xish477/ghast
Author-email: Alexis Rodriguez <arodriguez99@protonmail.com>
License-Expression: MIT
License-File: LICENSE
Classifier: Development Status :: 4 - Beta
Classifier: Programming Language :: Python
Classifier: Programming Language :: Python :: 3.7
Classifier: Programming Language :: Python :: 3.8
Classifier: Programming Language :: Python :: 3.9
Classifier: Programming Language :: Python :: 3.10
Classifier: Programming Language :: Python :: 3.11
Classifier: Programming Language :: Python :: Implementation :: CPython
Classifier: Programming Language :: Python :: Implementation :: PyPy
Requires-Python: >=3.7
Requires-Dist: iniconfig==2.0.0
Requires-Dist: packaging==23.1
Requires-Dist: pluggy==1.2.0
Requires-Dist: pytest==7.4.0
Requires-Dist: pyyaml==6.0
